README.rst
setup.py
django_simple_login.egg-info/PKG-INFO
django_simple_login.egg-info/SOURCES.txt
django_simple_login.egg-info/dependency_links.txt
django_simple_login.egg-info/requires.txt
django_simple_login.egg-info/top_level.txt
simple_login/__init__.py
simple_login/apps/__init__.py
simple_login/apps/config.py
simple_login/exceptions/__init__.py
simple_login/exceptions/api.py
simple_login/managers/__init__.py
simple_login/managers/api.py
simple_login/migrations/0001_initial.py
simple_login/migrations/__init__.py
simple_login/models/__init__.py
simple_login/models/api.py
simple_login/models/utils.py
simple_login/serializers/__init__.py
simple_login/serializers/api.py
simple_login/serializers/base.py
simple_login/utils/__init__.py
simple_login/utils/auth.py
simple_login/utils/email.py
simple_login/utils/otp.py
simple_login/utils/randomizer.py
simple_login/utils/social.py
simple_login/utils/user.py
simple_login/views/__init__.py
simple_login/views/api.py
simple_login/views/base.py